jaxdsp/__init__.py
jaxdsp/loss.py
jaxdsp/optimizers.py
jaxdsp/param.py
jaxdsp/params.py
jaxdsp/plotting.py
jaxdsp/processor_graph.py
jaxdsp/tracer.py
jaxdsp/training.py
jaxdsp/processors/__init__.py
jaxdsp/processors/allpass_filter.py
jaxdsp/processors/biquad_lowpass.py
jaxdsp/processors/clip.py
jaxdsp/processors/constants.py
jaxdsp/processors/delay_line.py
jaxdsp/processors/fir_filter.py
jaxdsp/processors/freeverb.py
jaxdsp/processors/iir_filter.py
jaxdsp/processors/lowpass_feedback_comb_filter.py
jaxdsp/processors/sine_wave.py
jaxdsp-0.3.1.dist-info/LICENSE
jaxdsp-0.3.1.dist-info/METADATA
jaxdsp-0.3.1.dist-info/WHEEL
jaxdsp-0.3.1.dist-info/top_level.txt
jaxdsp-0.3.1.dist-info/RECORD
