Metadata-Version: 2.1
Name: jaxdsp
Version: 0.3.1
Summary: Fast, differentiable audio processors on the CPU or GPU, with a browser client for real-time control
Home-page: https://github.com/khiner/jaxdsp
Author: Karl Hiner
Author-email: karl.hiner@gmail.com
License: UNKNOWN
Platform: UNKNOWN
Classifier: Programming Language :: Python :: 3
Classifier: License :: OSI Approved :: MIT License
Classifier: Operating System :: OS Independent
Requires-Python: >=3.8
License-File: LICENSE
Requires-Dist: jaxlib
Requires-Dist: jax[cpu]
